vk_slaves/__init__.py
vk_slaves/slaves.py
vk_slaves-1.2.0.dist-info/LICENSE
vk_slaves-1.2.0.dist-info/METADATA
vk_slaves-1.2.0.dist-info/WHEEL
vk_slaves-1.2.0.dist-info/top_level.txt
vk_slaves-1.2.0.dist-info/RECORD
