Metadata-Version: 2.1
Name: vk-slaves
Version: 1.2.0
Summary: Simple library for working with the VK Slaves
Home-page: https://github.com/MaxUNof/vk-slaves
Author: MaxUNof
Author-email: maxunof@pm.me
License: WTFPL
Download-URL: https://pypi.org/project/vk_slaves/
Keywords: VK,Slaves,VKSlaves
Platform: UNKNOWN
Requires-Dist: requests
Requires-Dist: fake-useragent
